{
  "model_type": "DecisionTreeClassifier",
  "best_params": {
    "ccp_alpha": 0.0,
    "class_weight": {
      "0": 1,
      "1": 5
    },
    "criterion": "gini",
    "max_depth": 5,
    "max_features": "sqrt",
    "max_leaf_nodes": null,
    "min_impurity_decrease": 0.0,
    "min_samples_leaf": 4,
    "min_samples_split": 20,
    "min_weight_fraction_leaf": 0.0,
    "splitter": "best"
  },
  "best_cv_f1": 0.48015455184758987,
  "auc_score": 0.7013523990007753,
  "thresholds": {
    "default": 0.5,
    "f1_optimized": 0.7534246575342466,
    "recall_optimized": 0.3125
  },
  "feature_importance": [
    {
      "Feature": "TotalWorkingYearsLog",
      "Importance": 0.3560574676436211
    },
    {
      "Feature": "OverTime_Yes",
      "Importance": 0.2261429268732726
    },
    {
      "Feature": "NumCompaniesWorked",
      "Importance": 0.14472722514586134
    },
    {
      "Feature": "WorkLifeBalance",
      "Importance": 0.07227591339043729
    },
    {
      "Feature": "Job_happiness_score",
      "Importance": 0.05562157899322077
    },
    {
      "Feature": "JobRole_Laboratory Technician",
      "Importance": 0.053035600046842206
    },
    {
      "Feature": "YearsAtCompanyLog",
      "Importance": 0.026857287755410197
    },
    {
      "Feature": "BusinessTravel_Travel_Frequently",
      "Importance": 0.017334017129827257
    },
    {
      "Feature": "JobRole_Manufacturing Director",
      "Importance": 0.016246669456616507
    },
    {
      "Feature": "MaritalStatus_Single",
      "Importance": 0.01196296264171431
    },
    {
      "Feature": "EnvironmentSatisfaction",
      "Importance": 0.011297885900901224
    },
    {
      "Feature": "JobRole_Healthcare Representative",
      "Importance": 0.008440465022275082
    },
    {
      "Feature": "JobSatisfaction",
      "Importance": 0.0
    },
    {
      "Feature": "JobInvolvement",
      "Importance": 0.0
    },
    {
      "Feature": "JobRole_Sales Representative",
      "Importance": 0.0
    },
    {
      "Feature": "Department_Research & Development",
      "Importance": 0.0
    },
    {
      "Feature": "JobRole_Research Director",
      "Importance": 0.0
    },
    {
      "Feature": "MaritalStatus_Married",
      "Importance": 0.0
    },
    {
      "Feature": "JobRole_Manager",
      "Importance": 0.0
    }
  ]
}